quick_crawler/__init__.py
quick_crawler/browser.py
quick_crawler/language.py
quick_crawler/multilang.py
quick_crawler/page.py
quick_crawler/utils.py
quick_crawler/__pycache__/__init__.cpython-36.pyc
quick_crawler/__pycache__/browser.cpython-36.pyc
quick_crawler/__pycache__/language.cpython-36.pyc
quick_crawler/__pycache__/multilang.cpython-36.pyc
quick_crawler/__pycache__/page.cpython-36.pyc
quick_crawler/__pycache__/utils.cpython-36.pyc
quick_crawler/pipline/__init__.py
quick_crawler/pipline/page_list.py
quick_crawler/scrapy_projects/__init__.py
quick_crawler/scrapy_projects/news_site/__init__.py
quick_crawler/scrapy_projects/news_site/scrapy.cfg
quick_crawler/scrapy_projects/news_site/news_site/__init__.py
quick_crawler/scrapy_projects/news_site/news_site/items.py
quick_crawler/scrapy_projects/news_site/news_site/middlewares.py
quick_crawler/scrapy_projects/news_site/news_site/pipelines.py
quick_crawler/scrapy_projects/news_site/news_site/settings.py
quick_crawler/scrapy_projects/news_site/news_site/settings_template.py
quick_crawler/scrapy_projects/news_site/news_site/__pycache__/__init__.cpython-36.pyc
quick_crawler/scrapy_projects/news_site/news_site/__pycache__/settings.cpython-36.pyc
quick_crawler/scrapy_projects/news_site/news_site/spiders/__init__.py
quick_crawler/scrapy_projects/news_site/news_site/spiders/news_spider.py
quick_crawler/scrapy_projects/news_site/news_site/spiders/news_spider_template.py
quick_crawler/scrapy_projects/news_site/news_site/spiders/__pycache__/__init__.cpython-36.pyc
quick_crawler/scrapy_projects/news_site/news_site/spiders/__pycache__/news_spider.cpython-36.pyc
quick_crawler/scrapy_projects/news_site/news_site/spiders/__pycache__/news_spider_template.cpython-36.pyc
quick_crawler-0.0.8.dist-info/LICENSE
quick_crawler-0.0.8.dist-info/METADATA
quick_crawler-0.0.8.dist-info/WHEEL
quick_crawler-0.0.8.dist-info/top_level.txt
quick_crawler-0.0.8.dist-info/RECORD
